LICENSE
MANIFEST.in
README.rst
setup.py
cache_dependencies/__init__.py
cache_dependencies/cache.py
cache_dependencies/defer.py
cache_dependencies/dependencies.py
cache_dependencies/exceptions.py
cache_dependencies/interfaces.py
cache_dependencies/locks.py
cache_dependencies/mixins.py
cache_dependencies/nocache.py
cache_dependencies/relations.py
cache_dependencies/tagging.py
cache_dependencies/transaction.py
cache_dependencies/utils.py
cache_dependencies.egg-info/PKG-INFO
cache_dependencies.egg-info/SOURCES.txt
cache_dependencies.egg-info/dependency_links.txt
cache_dependencies.egg-info/top_level.txt
cache_dependencies/tests/__init__.py
cache_dependencies/tests/helpers.py
cache_dependencies/tests/test_cache.py
cache_dependencies/tests/test_defer.py
cache_dependencies/tests/test_dependencies.py
cache_dependencies/tests/test_helpers.py
cache_dependencies/tests/test_locks.py
cache_dependencies/tests/test_relations.py
cache_dependencies/tests/test_tagging.py
cache_dependencies/tests/test_transaction.py
cache_tagging/__init__.py
cache_tagging/django_cache_tagging/__init__.py
django_cache_dependencies/__init__.py
django_cache_dependencies/backends.py
django_cache_dependencies/decorators.py
django_cache_dependencies/middleware.py
django_cache_dependencies/models.py
django_cache_dependencies/utils.py
django_cache_dependencies/management/__init__.py
django_cache_dependencies/management/commands/__init__.py
django_cache_dependencies/management/commands/cache_tagging_bench.py
django_cache_dependencies/templatetags/__init__.py
django_cache_dependencies/templatetags/cache_tagging_tags.py
django_cache_dependencies/tests/__init__.py
django_cache_dependencies/tests/urls.py
django_cache_dependencies/tests/views.py