Metadata-Version: 1.1
Name: cache-dependencies
Version: 0.7.7.41
Summary: Cache-dependencies (former Cache-tagging) allows you easily invalidate all cache records tagged with a given tag(s). Supports Django.
Home-page: https://bitbucket.org/emacsway/cache-dependencies
Author: Ivan Zakrevsky
Author-email: ivzak@yandex.ru
License: BSD License
Keywords: django cache dependencies tagging
Platform: UNKNOWN
Classifier: Development Status :: 5 - Production/Stable
Classifier: Environment :: Web Environment
Classifier: Framework :: Django
Classifier: Intended Audience :: Developers
Classifier: License :: OSI Approved :: BSD License
Classifier: Operating System :: OS Independent
Classifier: Programming Language :: Python
Classifier: Programming Language :: Python :: 2
Classifier: Programming Language :: Python :: 2.7
Classifier: Programming Language :: Python :: 3
Classifier: Programming Language :: Python :: 3.2
Classifier: Programming Language :: Python :: 3.3
Classifier: Programming Language :: Python :: 3.4
Classifier: Topic :: Software Development :: Libraries :: Application Frameworks
Classifier: Topic :: Software Development :: Libraries :: Python Modules
